flick/__init__.py
flick/api_service.py
flick/bills.py
flick_python_sdk-1.0.0.dist-info/LICENSE
flick_python_sdk-1.0.0.dist-info/METADATA
flick_python_sdk-1.0.0.dist-info/WHEEL
flick_python_sdk-1.0.0.dist-info/top_level.txt
flick_python_sdk-1.0.0.dist-info/RECORD
