Metadata-Version: 2.1
Name: flick-python-sdk
Version: 1.0.0
Summary: A Python wrapper for interacting with APIs from Flick.
Home-page: https://pypi.org/project/flick-python-sdk/
Author: Sivadas Rajan
Author-email: sivadasrajan@gmail.com
Maintainer: Sivadas Rajan
Maintainer-email: sivadasrajan@gmail.com
License: UNKNOWN
Project-URL: Bug Tracker, https://github.com/flick-network/flick-python-sdk/issues
Platform: UNKNOWN
Classifier: Programming Language :: Python :: 3
Classifier: License :: OSI Approved :: MIT License
Classifier: Operating System :: OS Independent
Requires-Python: >=3.6
License-File: LICENSE
Requires-Dist: aiohttp >=3.5.0
